[
    {"id": 1, "nombre": "Arroz", "tipo": "grano"},
    {"id": 2, "nombre": "Avena", "tipo": "grano"},
    {"id": 3, "nombre": "Maíz", "tipo": "grano"},
    {"id": 4, "nombre": "Trigo", "tipo": "grano"},
    {"id": 5, "nombre": "acelga", "tipo": "grano"},
    {"id": 6, "nombre": "ajo", "tipo": "grano"},
    {"id": 7, "nombre": "arveja", "tipo": "grano"},
    {"id": 8, "nombre": "batata", "tipo": "grano"},
    {"id": 9, "nombre": "berenjena", "tipo": "grano"},
    {"id": 10, "nombre": "brocoli", "tipo": "grano"},
    {"id": 11, "nombre": "cebolla", "tipo": "grano"},
    {"id": 12, "nombre": "coliflor", "tipo": "grano"},
    {"id": 13, "nombre": "espárrago", "tipo": "grano"},
    {"id": 14, "nombre": "espinaca", "tipo": "grano"},
    {"id": 15, "nombre": "garbanzo", "tipo": "grano"},
    {"id": 16, "nombre": "hinojo", "tipo": "grano"},
    {"id": 17, "nombre": "lenteja", "tipo": "grano"},
    {"id": 18, "nombre": "maní", "tipo": "grano"},
    {"id": 19, "nombre": "nabo", "tipo": "grano"},
    {"id": 20, "nombre": "papa", "tipo": "grano"},
    {"id": 21, "nombre": "pepino", "tipo": "grano"},
    {"id": 22, "nombre": "perejil", "tipo": "grano"},
    {"id": 23, "nombre": "pistacho", "tipo": "grano"},
    {"id": 24, "nombre": "poroto colorado", "tipo": "grano"},
    {"id": 25, "nombre": "poroto negro", "tipo": "grano"},
    {"id": 26, "nombre": "radicheta", "tipo": "grano"},
    {"id": 27, "nombre": "remolacha", "tipo": "grano"},
    {"id": 28, "nombre": "repollo", "tipo": "grano"},
    {"id": 29, "nombre": "soja", "tipo": "grano"},
    {"id": 30, "nombre": "tomate", "tipo": "grano"},
    {"id": 31, "nombre": "zanahoria", "tipo": "grano"},
    {"id": 32, "nombre": "zapallito", "tipo": "grano"},
    {"id": 33, "nombre": "zapallo", "tipo": "grano"},

    {"id": 34, "nombre": "aceituna verde", "tipo": "fruta"},
    {"id": 35, "nombre": "aceituna negra", "tipo": "fruta"},
    {"id": 36, "nombre": "ananá", "tipo": "fruta"},
    {"id": 37, "nombre": "banana", "tipo": "fruta"},
    {"id": 38, "nombre": "ciruela", "tipo": "fruta"},
    {"id": 39, "nombre": "coco", "tipo": "fruta"},
    {"id": 40, "nombre": "damasco", "tipo": "fruta"},
    {"id": 41, "nombre": "durazno", "tipo": "fruta"},
    {"id": 42, "nombre": "frutilla", "tipo": "fruta"},
    {"id": 44, "nombre": "limón", "tipo": "fruta"},
    {"id": 45, "nombre": "manzana", "tipo": "fruta"},
    {"id": 46, "nombre": "maracuyá", "tipo": "fruta"},
    {"id": 47, "nombre": "melón", "tipo": "fruta"},
    {"id": 48, "nombre": "membrillo", "tipo": "fruta"},
    {"id": 49, "nombre": "mora", "tipo": "fruta"},
    {"id": 50, "nombre": "palta", "tipo": "fruta"},
    {"id": 51, "nombre": "pera", "tipo": "fruta"},
    {"id": 52, "nombre": "pomelo", "tipo": "fruta"},
    {"id": 53, "nombre": "sandía", "tipo": "fruta"},

    {"id": 54, "nombre": "aceite de girasol", "tipo": "aceite"},
    {"id": 55, "nombre": "aceite de oliva", "tipo": "aceite"},
    {"id": 56, "nombre": "aceite de maíz", "tipo": "aceite"},

    {"id": 57, "nombre": "anchoa", "tipo": "pescado"},
    {"id": 58, "nombre": "boga", "tipo": "pescado"},
    {"id": 59, "nombre": "caballa", "tipo": "pescado"},
    {"id": 60, "nombre": "cornalito", "tipo": "pescado"},
    {"id": 61, "nombre": "merluza", "tipo": "pescado"},
    {"id": 62, "nombre": "pargo", "tipo": "pescado"},
    {"id": 63, "nombre": "pejerrey", "tipo": "pescado"},
    {"id": 64, "nombre": "surubí", "tipo": "pescado"},
    {"id": 65, "nombre": "calamar", "tipo": "pescado"},
    {"id": 66, "nombre": "centolla", "tipo": "pescado"},
    {"id": 67, "nombre": "langostino", "tipo": "pescado"},
    {"id": 68, "nombre": "mejillón", "tipo": "pescado"},

    {"id": 69, "nombre": "bola de lomo", "tipo": "carne"},
    {"id": 70, "nombre": "nalga", "tipo": "carne"},
    {"id": 71, "nombre": "peceto", "tipo": "carne"}
]